{
  "actions": [
    {
      "type": "createTable",
      "createTable": {
        "name": "artwork_comment",
        "dartName": "ArtworkComment",
        "module": "spectra",
        "schema": "public",
        "columns": [
          {
            "name": "id",
            "columnType": 6,
            "isNullable": false,
            "columnDefault": "nextval('artwork_comment_id_seq'::regclass)",
            "dartType": "int?"
          },
          {
            "name": "artworkId",
            "columnType": 6,
            "isNullable": false,
            "dartType": "int"
          },
          {
            "name": "ownerId",
            "columnType": 6,
            "isNullable": false,
            "dartType": "int"
          },
          {
            "name": "text",
            "columnType": 0,
            "isNullable": true,
            "dartType": "String?"
          },
          {
            "name": "dateCreated",
            "columnType": 4,
            "isNullable": true,
            "columnDefault": "CURRENT_TIMESTAMP",
            "dartType": "DateTime?"
          },
          {
            "name": "updatedAt",
            "columnType": 4,
            "isNullable": true,
            "dartType": "DateTime?"
          },
          {
            "name": "likesCount",
            "columnType": 6,
            "isNullable": true,
            "columnDefault": "0",
            "dartType": "int?"
          },
          {
            "name": "repliesCount",
            "columnType": 6,
            "isNullable": true,
            "columnDefault": "0",
            "dartType": "int?"
          },
          {
            "name": "parentId",
            "columnType": 6,
            "isNullable": true,
            "dartType": "int?"
          },
          {
            "name": "isDeleted",
            "columnType": 1,
            "isNullable": true,
            "columnDefault": "false",
            "dartType": "bool?"
          }
        ],
        "foreignKeys": [
          {
            "constraintName": "artwork_comment_fk_0",
            "columns": [
              "artworkId"
            ],
            "referenceTable": "artwork",
            "referenceTableSchema": "public",
            "referenceColumns": [
              "id"
            ],
            "onUpdate": 3,
            "onDelete": 3
          },
          {
            "constraintName": "artwork_comment_fk_1",
            "columns": [
              "ownerId"
            ],
            "referenceTable": "user",
            "referenceTableSchema": "public",
            "referenceColumns": [
              "id"
            ],
            "onUpdate": 3,
            "onDelete": 3
          },
          {
            "constraintName": "artwork_comment_fk_2",
            "columns": [
              "parentId"
            ],
            "referenceTable": "artwork_comment",
            "referenceTableSchema": "public",
            "referenceColumns": [
              "id"
            ],
            "onUpdate": 3,
            "onDelete": 3
          }
        ],
        "indexes": [
          {
            "indexName": "artwork_comment_pkey",
            "elements": [
              {
                "type": 0,
                "definition": "id"
              }
            ],
            "type": "btree",
            "isUnique": true,
            "isPrimary": true
          }
        ],
        "managed": true
      }
    },
    {
      "type": "createTable",
      "createTable": {
        "name": "artwork_comment_likes",
        "dartName": "ArtworkCommentLikes",
        "module": "spectra",
        "schema": "public",
        "columns": [
          {
            "name": "id",
            "columnType": 6,
            "isNullable": false,
            "columnDefault": "nextval('artwork_comment_likes_id_seq'::regclass)",
            "dartType": "int?"
          },
          {
            "name": "artworkCommentId",
            "columnType": 6,
            "isNullable": false,
            "dartType": "int"
          },
          {
            "name": "likedById",
            "columnType": 6,
            "isNullable": false,
            "dartType": "int"
          },
          {
            "name": "dateCreated",
            "columnType": 4,
            "isNullable": true,
            "columnDefault": "CURRENT_TIMESTAMP",
            "dartType": "DateTime?"
          }
        ],
        "foreignKeys": [
          {
            "constraintName": "artwork_comment_likes_fk_0",
            "columns": [
              "artworkCommentId"
            ],
            "referenceTable": "artwork_comment",
            "referenceTableSchema": "public",
            "referenceColumns": [
              "id"
            ],
            "onUpdate": 3,
            "onDelete": 4
          },
          {
            "constraintName": "artwork_comment_likes_fk_1",
            "columns": [
              "likedById"
            ],
            "referenceTable": "user",
            "referenceTableSchema": "public",
            "referenceColumns": [
              "id"
            ],
            "onUpdate": 3,
            "onDelete": 3
          }
        ],
        "indexes": [
          {
            "indexName": "artwork_comment_likes_pkey",
            "elements": [
              {
                "type": 0,
                "definition": "id"
              }
            ],
            "type": "btree",
            "isUnique": true,
            "isPrimary": true
          },
          {
            "indexName": "artwork_comment_likes_unique_idx",
            "elements": [
              {
                "type": 0,
                "definition": "artworkCommentId"
              },
              {
                "type": 0,
                "definition": "likedById"
              }
            ],
            "type": "btree",
            "isUnique": true,
            "isPrimary": false
          }
        ],
        "managed": true
      }
    }
  ],
  "warnings": [],
  "migrationApiVersion": 1
}